neuspell/__init__.py
neuspell/commons.py
neuspell/corrector_aspell.py
neuspell/corrector_bertsclstm.py
neuspell/corrector_cnnlstm.py
neuspell/corrector_elmosclstm.py
neuspell/corrector_jamspell.py
neuspell/corrector_lstmlstm.py
neuspell/corrector_sclstm.py
neuspell/corrector_sclstmbert.py
neuspell/corrector_sclstmelmo.py
neuspell/corrector_subwordbert.py
neuspell/seq_modeling/__init__.py
neuspell/seq_modeling/bertsclstm.py
neuspell/seq_modeling/cnnlstm.py
neuspell/seq_modeling/downloads.py
neuspell/seq_modeling/elmosclstm.py
neuspell/seq_modeling/elmosctrans.py
neuspell/seq_modeling/evals.py
neuspell/seq_modeling/helpers.py
neuspell/seq_modeling/helpers2.py
neuspell/seq_modeling/lstmlstm.py
neuspell/seq_modeling/models.py
neuspell/seq_modeling/sclstm.py
neuspell/seq_modeling/sclstmbert.py
neuspell/seq_modeling/sclstmelmo.py
neuspell/seq_modeling/subwordbert.py
neuspell/seq_modeling/subwordelmo.py
neuspell/seq_modeling/util.py
scripts/__init__.py
scripts/evals.py
scripts/baselines/__init__.py
scripts/candidate_generation_reranking/__init__.py
scripts/candidate_generation_reranking/candidate.py
scripts/candidate_generation_reranking/candidates_generation.py
scripts/candidate_generation_reranking/candidates_reranking.py
scripts/candidate_generation_reranking/double_metaphone.py
scripts/candidate_generation_reranking/downloads.py
scripts/candidate_generation_reranking/edit_distance.py
scripts/candidate_generation_reranking/vocab.py
scripts/seq_modeling/__init__.py
scripts/seq_modeling/bertsclstm.py
scripts/seq_modeling/cnnlstm.py
scripts/seq_modeling/elmosclstm.py
scripts/seq_modeling/elmosctrans.py
scripts/seq_modeling/helpers.py
scripts/seq_modeling/helpers2.py
scripts/seq_modeling/lstmlstm.py
scripts/seq_modeling/models.py
scripts/seq_modeling/sclstm.py
scripts/seq_modeling/sclstmbert.py
scripts/seq_modeling/sclstmelmo.py
scripts/seq_modeling/subwordbert.py
scripts/seq_modeling/subwordelmo.py
neuspell-1.0.0.dist-info/LICENSE
neuspell-1.0.0.dist-info/METADATA
neuspell-1.0.0.dist-info/WHEEL
neuspell-1.0.0.dist-info/top_level.txt
neuspell-1.0.0.dist-info/RECORD
