Metadata-Version: 2.1
Name: neuspell
Version: 1.0.0
Summary: NeuSpell: A Neural Spelling Correction Toolkit
Home-page: https://github.com/neuspell/neuspell
Author: Sai Muralidhar Jayanthi, Danish Pruthi, and Graham Neubig
Author-email: jsaimurali001@gmail.com
License: MIT
Keywords: transformer networks neuspell neural spelling correction embedding PyTorch NLP deep learning
Platform: UNKNOWN
Classifier: Natural Language :: English
Classifier: Intended Audience :: Science/Research
Classifier: Programming Language :: Python :: 3.6
Classifier: Programming Language :: Python :: 3.7
Classifier: Topic :: Scientific/Engineering :: Artificial Intelligence
Classifier: License :: OSI Approved :: MIT License
Requires-Python: >3.5
Requires-Dist: transformers
Requires-Dist: tqdm
Requires-Dist: torch (>=1.6.0)
Requires-Dist: numpy
Requires-Dist: jsonlines
Requires-Dist: sentencepiece
Requires-Dist: pytorch-pretrained-bert
Provides-Extra: elmo
Requires-Dist: allennlp (==1.5.0) ; extra == 'elmo'
Provides-Extra: spacy
Requires-Dist: spacy ; extra == 'spacy'
